vk_urls_validator/__init__.py
vk_urls_validator/validator.py
vk_urls_validator/utils/__init__.py
vk_urls_validator/utils/exceptions.py
vk_urls_validator/utils/utils.py
vk_urls_validator-0.0.4.dist-info/LICENSE
vk_urls_validator-0.0.4.dist-info/METADATA
vk_urls_validator-0.0.4.dist-info/WHEEL
vk_urls_validator-0.0.4.dist-info/top_level.txt
vk_urls_validator-0.0.4.dist-info/RECORD
