Metadata-Version: 2.1
Name: vk_urls_validator
Version: 0.0.4
Summary: Validator for VK URLs.
Home-page: https://github.com/Wiped-Out/vk_urls_validator
Download-URL: https://github.com/Wiped-Out/vk_urls_validator/releases/latest
Author: Emir Takhaviev
Author-email: tah116emir@outlook.com
Keywords: python,vk urls,validation
Classifier: Development Status :: 3 - Alpha
Classifier: Intended Audience :: Developers
Classifier: Programming Language :: Python :: 3
Classifier: Operating System :: Unix
Classifier: Operating System :: MacOS :: MacOS X
Classifier: Operating System :: Microsoft :: Windows
License-File: LICENSE
